fluid_design/README.rst
fluid_design/__init__.py
fluid_design/apps.py
fluid_design/mithril-js/messages.json
fluid_design/static/fluid_design/fluid-design-system.css
fluid_design/static/fluid_design/fluid-design-system.js
fluid_design/tags/__init__.py
fluid_design/tags/autocomplete.py
fluid_design/tags/avatar.py
fluid_design/tags/badge.py
fluid_design/tags/base.py
fluid_design/tags/base_widgets.py
fluid_design/tags/breadcrumb.py
fluid_design/tags/button.py
fluid_design/tags/card.py
fluid_design/tags/checkbox.py
fluid_design/tags/collapse.py
fluid_design/tags/fab.py
fluid_design/tags/footer.py
fluid_design/tags/form_item.py
fluid_design/tags/grid.py
fluid_design/tags/header.py
fluid_design/tags/icon.py
fluid_design/tags/icon_button.py
fluid_design/tags/inline_message.py
fluid_design/tags/link.py
fluid_design/tags/list_.py
fluid_design/tags/modal.py
fluid_design/tags/navbar.py
fluid_design/tags/pagination.py
fluid_design/tags/progress.py
fluid_design/tags/radio_set.py
fluid_design/tags/segmented_control.py
fluid_design/tags/sidebar.py
fluid_design/tags/skeleton.py
fluid_design/tags/slider.py
fluid_design/tags/spinner.py
fluid_design/tags/stamp.py
fluid_design/tags/status_indicator.py
fluid_design/tags/table.py
fluid_design/tags/tabs.py
fluid_design/tags/tag.py
fluid_design/tags/toast.py
fluid_design/tags/toggle.py
fluid_design/templatetags/__init__.py
fluid_design/templatetags/fluid_design.py
fluid_design/utils/__init__.py
fluid_design/utils/formats.py
django_fluid_design-0.0.2.dist-info/LICENSE
django_fluid_design-0.0.2.dist-info/METADATA
django_fluid_design-0.0.2.dist-info/WHEEL
django_fluid_design-0.0.2.dist-info/top_level.txt
django_fluid_design-0.0.2.dist-info/RECORD
