Metadata-Version: 2.1
Name: django-fluid-design
Version: 0.0.2
Summary: Fluid Design System in Django templates
Home-page: https://codeberg.org/dozymoe/django-fluid-design
Author: Fahri Reza
Author-email: dozymoe@gmail.com
License: MIT
Project-URL: Bug Tracker, https://codeberg.org/dozymoe/django-fluid-design/issues
Classifier: Environment :: Web Environment
Classifier: Framework :: Django
Classifier: Intended Audience :: Developers
Classifier: License :: OSI Approved :: MIT License
Classifier: Operating System :: OS Independent
Classifier: Programming Language :: Python
Classifier: Programming Language :: Python :: 3
Classifier: Topic :: Internet :: WWW/HTTP
Classifier: Topic :: Internet :: WWW/HTTP :: Dynamic Content
License-File: LICENSE
Requires-Dist: django
Requires-Dist: lxml
Requires-Dist: pytz
